apidatawho/__init__.py
apidatawho/apidatawho.py
apidatawho/whoami.py
apidatawho-0.0.8.dist-info/LICENSE.txt
apidatawho-0.0.8.dist-info/METADATA
apidatawho-0.0.8.dist-info/WHEEL
apidatawho-0.0.8.dist-info/top_level.txt
apidatawho-0.0.8.dist-info/RECORD
