Metadata-Version: 2.1
Name: apidatawho
Version: 0.0.8
Summary: Getting the world helth organization data using WHO API
Home-page: https://github.com/deepstartup/WHOAPIdata
Author: Arghadeep Chaudhury,Siddhartha Bhattacharya
Author-email: siddhartha.bhattacharya@in.ibm.com,arghadeep.chaudhury@gmail.com
License: UNKNOWN
Platform: UNKNOWN
Classifier: Programming Language :: Python :: 3
Classifier: License :: OSI Approved :: MIT License
Classifier: Operating System :: OS Independent
Requires-Dist: pandas
Requires-Dist: requests
Requires-Dist: json2xml
Requires-Dist: pyyaml
